ipytree/__init__.py
ipytree/_version.py
ipytree/tree.py
ipytree/labextension/package.json
ipytree/labextension/static/261.4efb75b6352af894acb4.js
ipytree/labextension/static/287.fd063a1253f3266560f7.js
ipytree/labextension/static/287.fd063a1253f3266560f7.js.LICENSE.txt
ipytree/labextension/static/486.4c1ca47efc3790912711.js
ipytree/labextension/static/486.4c1ca47efc3790912711.js.LICENSE.txt
ipytree/labextension/static/568.c44c0ae4f70f7df0fe86.js
ipytree/labextension/static/755.71bcc770291b01d6ebaa.js
ipytree/labextension/static/755.71bcc770291b01d6ebaa.js.LICENSE.txt
ipytree/labextension/static/remoteEntry.a322e5c11f9830cf62f6.js
ipytree/labextension/static/style.js
ipytree/labextension/static/third-party-licenses.json
ipytree/nbextension/extension.js
ipytree/nbextension/index.js
ipytree/nbextension/index.js.LICENSE.txt
ipytree/nbextension/index.js.map
ipytree-0.2.2.data/data/etc/jupyter/nbconfig/notebook.d/ipytree.json
ipytree-0.2.2.data/data/share/jupyter/labextensions/ipytree/package.json
ipytree-0.2.2.data/data/share/jupyter/labextensions/ipytree/static/261.4efb75b6352af894acb4.js
ipytree-0.2.2.data/data/share/jupyter/labextensions/ipytree/static/287.fd063a1253f3266560f7.js
ipytree-0.2.2.data/data/share/jupyter/labextensions/ipytree/static/287.fd063a1253f3266560f7.js.LICENSE.txt
ipytree-0.2.2.data/data/share/jupyter/labextensions/ipytree/static/486.4c1ca47efc3790912711.js
ipytree-0.2.2.data/data/share/jupyter/labextensions/ipytree/static/486.4c1ca47efc3790912711.js.LICENSE.txt
ipytree-0.2.2.data/data/share/jupyter/labextensions/ipytree/static/568.c44c0ae4f70f7df0fe86.js
ipytree-0.2.2.data/data/share/jupyter/labextensions/ipytree/static/755.71bcc770291b01d6ebaa.js
ipytree-0.2.2.data/data/share/jupyter/labextensions/ipytree/static/755.71bcc770291b01d6ebaa.js.LICENSE.txt
ipytree-0.2.2.data/data/share/jupyter/labextensions/ipytree/static/remoteEntry.a322e5c11f9830cf62f6.js
ipytree-0.2.2.data/data/share/jupyter/labextensions/ipytree/static/style.js
ipytree-0.2.2.dist-info/LICENSE
ipytree-0.2.2.dist-info/METADATA
ipytree-0.2.2.dist-info/WHEEL
ipytree-0.2.2.dist-info/top_level.txt
ipytree-0.2.2.dist-info/RECORD
